[
  {
    "nombre": "Amoxicilina",
    "presentacion": "500 mg cápsula / 250 mg/5 ml suspensión",
    "via": "Oral",
    "dosisAdulto": "500 mg cada 8 horas",
    "dosisPediatrica": "20-40 mg/kg/día cada 8 horas",
    "maximoDiario": "3000 mg/día",
    "contraindicaciones": "Hipersensibilidad a penicilinas, mononucleosis infecciosa",
    "interacciones": "Metotrexato, warfarina, alopurinol",
    "indicaciones": "Infecciones respiratorias, otitis media, sinusitis, infecciones urinarias",
    "icono": "shieldPlus",
    "categoria": "antibiotico"
  },
  {
    "nombre": "Ciprofloxacino",
    "presentacion": "250 mg, 500 mg, 750 mg comprimidos",
    "via": "Oral, EV",
    "dosisAdulto": "250-750 mg cada 12 horas",
    "dosisPediatrica": "10-20 mg/kg cada 12 horas (uso restringido)",
    "maximoDiario": "1500 mg/día",
    "contraindicaciones": "Hipersensibilidad a quinolonas, epilepsia, tendinitis previa",
    "interacciones": "Antiácidos, teofilina, warfarina, AINEs",
    "indicaciones": "Infecciones urinarias, gastrointestinales, respiratorias, osteomielitis",
    "icono": "shieldPlus",
    "categoria": "antibiotico"
  },
  {
    "nombre": "Azitromicina",
    "presentacion": "250 mg, 500 mg comprimidos / 200 mg/5 ml suspensión",
    "via": "Oral, EV",
    "dosisAdulto": "500 mg el día 1, luego 250 mg días 2-5",
    "dosisPediatrica": "10 mg/kg el día 1, luego 5 mg/kg días 2-5",
    "maximoDiario": "500 mg/día",
    "contraindicaciones": "Hipersensibilidad a macrólidos, hepatopatía grave",
    "interacciones": "Anticoagulantes, digoxina, colchicina, estatinas",
    "indicaciones": "Infecciones respiratorias, faringitis, amigdalitis, infecciones de piel",
    "icono": "shieldPlus",
    "categoria": "antibiotico"
  },
  {
    "nombre": "Paracetamol",
    "presentacion": "500 mg comprimido / 120 mg/5 ml suspensión",
    "via": "Oral, EV",
    "dosisAdulto": "500-1000 mg cada 6-8h",
    "dosisPediatrica": "10-15 mg/kg cada 6-8h",
    "maximoDiario": "4000 mg/día",
    "contraindicaciones": "Insuficiencia hepática grave, hipersensibilidad",
    "interacciones": "Alcohol, warfarina, fenitoína",
    "indicaciones": "Dolor leve a moderado, fiebre",
    "icono": "bandaids",
    "categoria": "analgesico"
  },
  {
    "nombre": "Ibuprofeno",
    "presentacion": "400 mg, 600 mg comprimidos / 100 mg/5 ml suspensión",
    "via": "Oral",
    "dosisAdulto": "400-600 mg cada 6-8h",
    "dosisPediatrica": "5-10 mg/kg cada 6-8h",
    "maximoDiario": "2400 mg/día",
    "contraindicaciones": "Úlcera péptica activa, insuficiencia renal grave",
    "interacciones": "AAS, anticoagulantes, litio",
    "indicaciones": "Dolor, inflamación, fiebre",
    "icono": "bandaids",
    "categoria": "analgesico"
  },
  {
    "nombre": "Ketorolaco",
    "presentacion": "10 mg comprimidos / 30 mg/ml ampolla",
    "via": "Oral, IM, EV",
    "dosisAdulto": "10 mg cada 6-8h (oral), 30 mg IM/EV",
    "dosisPediatrica": "No recomendado en niños",
    "maximoDiario": "40 mg/día (oral), 120 mg/día (IM/EV)",
    "contraindicaciones": "Hipersensibilidad a AINEs, hemorragia activa",
    "interacciones": "AAS, anticoagulantes, metotrexato",
    "indicaciones": "Dolor agudo moderado a severo",
    "icono": "bandaids",
    "categoria": "analgesico"
  },
  {
    "nombre": "Metoprolol",
    "presentacion": "50 mg, 100 mg comprimidos",
    "via": "Oral, EV",
    "dosisAdulto": "50-100 mg cada 12-24h",
    "dosisPediatrica": "1-2 mg/kg/día",
    "maximoDiario": "400 mg/día",
    "contraindicaciones": "Bradicardia severa, bloqueo AV, asma",
    "interacciones": "Verapamilo, digoxina, clonidina",
    "indicaciones": "Hipertensión, angina, insuficiencia cardíaca",
    "icono": "heartbeat",
    "categoria": "antihipertensivo"
  },
  {
    "nombre": "Enalapril",
    "presentacion": "5 mg, 10 mg, 20 mg comprimidos",
    "via": "Oral",
    "dosisAdulto": "5-20 mg/día en 1-2 dosis",
    "dosisPediatrica": "0.1-0.5 mg/kg/día",
    "maximoDiario": "40 mg/día",
    "contraindicaciones": "Estenosis de arteria renal, embarazo",
    "interacciones": "AINEs, diuréticos ahorradores de potasio",
    "indicaciones": "Hipertensión, insuficiencia cardíaca",
    "icono": "heartbeat",
    "categoria": "antihipertensivo"
  },
  {
    "nombre": "Digoxina",
    "presentacion": "0.25 mg comprimidos / 0.5 mg/2 ml ampolla",
    "via": "Oral, EV",
    "dosisAdulto": "0.125-0.25 mg/día",
    "dosisPediatrica": "10-15 µg/kg/día",
    "maximoDiario": "0.5 mg/día",
    "contraindicaciones": "Intoxicación digitálica, miocardiopatía hipertrófica",
    "interacciones": "Amiodarona, verapamilo, diuréticos",
    "indicaciones": "Insuficiencia cardíaca, fibrilación auricular",
    "icono": "heartbeat",
    "categoria": "antihipertrensivo"
  }
]